{
  "id": "joel-ortega-cuevas",
  "name": "Joel Ortega Cuevas",
  "avatarUrl": "http://i.imgur.com/L6feLja.png",
  "description": "Director General del Sistema de Transporte Colectivo",
  "social": {
    "twitter": {
      "username": "JoelOrtegaCueva"
    }
  },
  "partyLog": [
    {
      "id": "none",
      "acronym": "(desconocido)",
      "duration": null,
      "durationPercentage": 100
    }
  ],
  "positions": [
    {
      "title": "Director General del Sistema de Transporte Colectivo",
      "interval": "2012 (actual)"
    },
    {
      "title": "Secretario de Seguridad Pública de Distrito Federal",
      "interval": "2004-2008"
    },
    {
      "title": "Jefe delegacional de Gustavo A. Madero",
      "interval": "2000-2003"
    }
  ]
}
